{"version":1,"resource":"file:///home/lewisb/documents/repos/brittonsbash/src/components/bash-blocks/header/header.component.tsx","entries":[{"id":"cEl8.tsx","timestamp":1697278432019},{"id":"9tyw.tsx","timestamp":1697278457283},{"id":"qpSc.tsx","timestamp":1697278513163},{"id":"QFLe.tsx","timestamp":1697278536893},{"id":"6SvV.tsx","timestamp":1697278636853},{"id":"6B0Z.tsx","timestamp":1697278719809},{"id":"lBDc.tsx","timestamp":1697278818133},{"id":"a6S1.tsx","timestamp":1697279084399},{"id":"27f3.tsx","timestamp":1697279095799},{"id":"9cMY.tsx","timestamp":1697279125189},{"id":"Yyrv.tsx","timestamp":1697279141713},{"id":"NfLh.tsx","timestamp":1697279161976},{"id":"lB9w.tsx","timestamp":1697279288536},{"id":"cDeX.tsx","timestamp":1697279301533},{"id":"Y0Yn.tsx","timestamp":1697279322213},{"id":"Hq7p.tsx","timestamp":1697279422216},{"id":"Yop1.tsx","timestamp":1697280068636},{"id":"fTYK.tsx","timestamp":1697280097906},{"id":"YVj2.tsx","timestamp":1697280177396},{"id":"lCXR.tsx","timestamp":1697280264986},{"id":"HkEb.tsx","timestamp":1697280366069},{"id":"GMUR.tsx","timestamp":1697280492129},{"id":"I81d.tsx","timestamp":1697280572783},{"id":"aBk5.tsx","timestamp":1697280629066},{"id":"SP9D.tsx","timestamp":1697280650783},{"id":"PCn8.tsx","timestamp":1697280663399},{"id":"XN0W.tsx","timestamp":1697280689553},{"id":"iBwY.tsx","timestamp":1697281909343},{"id":"CFZS.tsx","timestamp":1697281936119},{"id":"jJ6k.tsx","timestamp":1697282085083},{"id":"9iwW.tsx","timestamp":1697282140946},{"id":"Hij8.tsx","timestamp":1697282161863},{"id":"f47f.tsx","timestamp":1697282176476},{"id":"kXEh.tsx","timestamp":1697282225559},{"id":"fyMj.tsx","timestamp":1697282243716},{"id":"hCp3.tsx","timestamp":1697282275176},{"id":"ErVe.tsx","source":"undoRedo.source","timestamp":1697282279013},{"id":"vG3o.tsx","timestamp":1697282430343},{"id":"gELH.tsx","timestamp":1697282468009},{"id":"Gib1.tsx","timestamp":1697282940279},{"id":"SeaI.tsx","timestamp":1697358154502},{"id":"xe4d.tsx","timestamp":1698010748146},{"id":"aqsk.tsx","timestamp":1698010817669},{"id":"Cn2P.tsx","timestamp":1698011964649},{"id":"0b0S.tsx","timestamp":1701636578896},{"id":"t5t6.tsx","timestamp":1701636623966},{"id":"aUpt.tsx","timestamp":1701636638813},{"id":"mm5A.tsx","source":"undoRedo.source","timestamp":1701636643399},{"id":"E5tF.tsx","timestamp":1701636650719},{"id":"DbLs.tsx","timestamp":1701636727753}]}